{
	"abstract" : true,
	"backtrace" : 1,
	"backtraceGraph" : 
	{
		"commands" : 
		[
			"add_library",
			"target_link_libraries"
		],
		"files" : 
		[
			"build/_deps/boost-src/libs/log/CMakeLists.txt"
		],
		"nodes" : 
		[
			{
				"file" : 0
			},
			{
				"command" : 0,
				"file" : 0,
				"line" : 557,
				"parent" : 0
			},
			{
				"command" : 1,
				"file" : 0,
				"line" : 560,
				"parent" : 0
			}
		]
	},
	"codemodelVersion" : 
	{
		"major" : 2,
		"minor" : 9
	},
	"id" : "boost_log_with_support::@d73e606139ecf3097288",
	"interfaceCompileDependencies" : 
	[
		{
			"backtrace" : 2,
			"id" : "boost_log::@d73e606139ecf3097288"
		},
		{
			"backtrace" : 2,
			"id" : "boost_exception::@99a4a3f312800b24f965"
		},
		{
			"backtrace" : 2,
			"id" : "boost_regex::@581c0f51b3ce05b0d2f8"
		},
		{
			"backtrace" : 2,
			"id" : "boost_spirit::@5e5f17adf0e91bdf2f22"
		},
		{
			"backtrace" : 2,
			"id" : "boost_xpressive::@4512d8448885369db370"
		}
	],
	"interfaceLinkLibraries" : 
	[
		{
			"backtrace" : 2,
			"id" : "boost_log::@d73e606139ecf3097288"
		},
		{
			"backtrace" : 2,
			"id" : "boost_exception::@99a4a3f312800b24f965"
		},
		{
			"backtrace" : 2,
			"id" : "boost_regex::@581c0f51b3ce05b0d2f8"
		},
		{
			"backtrace" : 2,
			"id" : "boost_spirit::@5e5f17adf0e91bdf2f22"
		},
		{
			"backtrace" : 2,
			"id" : "boost_xpressive::@4512d8448885369db370"
		}
	],
	"name" : "boost_log_with_support",
	"paths" : 
	{
		"build" : "_deps/boost-build/libs/log",
		"source" : "build/_deps/boost-src/libs/log"
	},
	"sources" : [],
	"type" : "INTERFACE_LIBRARY"
}
