{
	"abstract" : true,
	"backtrace" : 1,
	"backtraceGraph" : 
	{
		"commands" : 
		[
			"add_library",
			"target_link_libraries"
		],
		"files" : 
		[
			"build/_deps/boost-src/libs/asio/CMakeLists.txt"
		],
		"nodes" : 
		[
			{
				"file" : 0
			},
			{
				"command" : 0,
				"file" : 0,
				"line" : 13,
				"parent" : 0
			},
			{
				"command" : 1,
				"file" : 0,
				"line" : 18,
				"parent" : 0
			}
		]
	},
	"codemodelVersion" : 
	{
		"major" : 2,
		"minor" : 9
	},
	"id" : "boost_asio_core::@2c95fe3a48624767d706",
	"interfaceCompileDependencies" : 
	[
		{
			"backtrace" : 2,
			"id" : "boost_align::@797bcbbb5a46605b8839"
		},
		{
			"backtrace" : 2,
			"id" : "boost_assert::@ca781959373d446383c8"
		},
		{
			"backtrace" : 2,
			"id" : "boost_config::@8fd7e5fcb366bce5ccde"
		},
		{
			"backtrace" : 2,
			"id" : "boost_system::@88f8acc0de176ce32d14"
		},
		{
			"backtrace" : 2,
			"id" : "boost_throw_exception::@83cb61eed02efd6dd30e"
		}
	],
	"interfaceLinkLibraries" : 
	[
		{
			"backtrace" : 2,
			"id" : "boost_align::@797bcbbb5a46605b8839"
		},
		{
			"backtrace" : 2,
			"id" : "boost_assert::@ca781959373d446383c8"
		},
		{
			"backtrace" : 2,
			"id" : "boost_config::@8fd7e5fcb366bce5ccde"
		},
		{
			"backtrace" : 2,
			"id" : "boost_system::@88f8acc0de176ce32d14"
		},
		{
			"backtrace" : 2,
			"id" : "boost_throw_exception::@83cb61eed02efd6dd30e"
		}
	],
	"name" : "boost_asio_core",
	"paths" : 
	{
		"build" : "_deps/boost-build/libs/asio",
		"source" : "build/_deps/boost-src/libs/asio"
	},
	"sources" : [],
	"type" : "INTERFACE_LIBRARY"
}
