{
	"abstract" : true,
	"backtrace" : 1,
	"backtraceGraph" : 
	{
		"commands" : 
		[
			"add_library"
		],
		"files" : 
		[
			"build/_deps/boost-src/libs/lambda2/CMakeLists.txt"
		],
		"nodes" : 
		[
			{
				"file" : 0
			},
			{
				"command" : 0,
				"file" : 0,
				"line" : 10,
				"parent" : 0
			}
		]
	},
	"codemodelVersion" : 
	{
		"major" : 2,
		"minor" : 9
	},
	"id" : "boost_lambda2::@e8bdc6883f73ae47898a",
	"name" : "boost_lambda2",
	"paths" : 
	{
		"build" : "_deps/boost-build/libs/lambda2",
		"source" : "build/_deps/boost-src/libs/lambda2"
	},
	"sources" : [],
	"type" : "INTERFACE_LIBRARY"
}
