{
	"abstract" : true,
	"backtrace" : 1,
	"backtraceGraph" : 
	{
		"commands" : 
		[
			"add_library",
			"target_link_libraries"
		],
		"files" : 
		[
			"build/_deps/boost-src/libs/polygon/CMakeLists.txt"
		],
		"nodes" : 
		[
			{
				"file" : 0
			},
			{
				"command" : 0,
				"file" : 0,
				"line" : 11,
				"parent" : 0
			},
			{
				"command" : 1,
				"file" : 0,
				"line" : 17,
				"parent" : 0
			}
		]
	},
	"codemodelVersion" : 
	{
		"major" : 2,
		"minor" : 9
	},
	"id" : "boost_polygon::@3f41c68ac52195297a3f",
	"interfaceCompileDependencies" : 
	[
		{
			"backtrace" : 2,
			"id" : "boost_config::@8fd7e5fcb366bce5ccde"
		}
	],
	"interfaceLinkLibraries" : 
	[
		{
			"backtrace" : 2,
			"id" : "boost_config::@8fd7e5fcb366bce5ccde"
		}
	],
	"name" : "boost_polygon",
	"paths" : 
	{
		"build" : "_deps/boost-build/libs/polygon",
		"source" : "build/_deps/boost-src/libs/polygon"
	},
	"sources" : [],
	"type" : "INTERFACE_LIBRARY"
}
